<PAMDataset>
  <PAMRasterBand band="1">
    <Histograms>
      <HistItem>
        <HistMin>8.883586883544901</HistMin>
        <HistMax>21.009559631348</HistMax>
        <BucketCount>256</BucketCount>
        <IncludeOutOfRange>1</IncludeOutOfRange>
        <Approximate>0</Approximate>
        <HistCounts>1|0|1|0|0|3|1|0|1|3|0|1|3|2|0|4|5|1|2|7|1|7|4|3|8|1|10|5|8|2|3|9|6|5|12|5|7|11|8|5|13|6|12|14|7|4|13|12|13|15|9|12|14|11|12|19|12|16|24|21|12|19|15|19|17|24|20|28|30|28|35|36|38|33|27|34|44|31|25|46|35|40|33|60|53|47|66|62|55|64|63|70|65|55|60|74|82|88|77|104|98|92|97|87|101|129|131|135|143|147|107|156|148|142|165|153|186|184|186|185|194|200|198|207|211|230|235|229|248|258|257|254|244|272|293|308|303|337|349|343|344|381|419|368|394|418|380|440|438|481|448|540|541|556|516|554|560|573|570|656|701|651|722|654|773|756|780|863|883|897|927|919|965|1039|1070|1104|1147|1209|1227|1386|1412|1398|1519|1595|1663|1813|1872|1961|2191|2153|2456|2460|2611|2619|2730|2848|3002|3285|3518|3566|3882|4410|4679|5074|5943|7084|8165|7919|4274|2477|2055|2007|2027|1753|1564|1446|1291|1159|1206|1064|987|869|833|785|787|751|769|741|696|695|671|617|586|597|400|340|335|262|187|127|91|84|36|45|25|21|11|7|2|4|0|0|0|0|1|0</HistCounts>
      </HistItem>
    </Histograms>
    <Metadata>
      <MDI key="STATISTICS_COVARIANCES">1.739802872334862</MDI>
      <MDI key="STATISTICS_MAXIMUM">21.009559631348</MDI>
      <MDI key="STATISTICS_MEAN">17.988116774707</MDI>
      <MDI key="STATISTICS_MINIMUM">8.8835868835449</MDI>
      <MDI key="STATISTICS_SKIPFACTORX">1</MDI>
      <MDI key="STATISTICS_SKIPFACTORY">1</MDI>
      <MDI key="STATISTICS_STDDEV">1.3190158726622</MDI>
    </Metadata>
  </PAMRasterBand>
</PAMDataset>
